README.md
setup.cfg
setup.py
sclassifier/__init__.py
sclassifier/classifier.py
sclassifier/classifier_nn.py
sclassifier/clustering.py
sclassifier/cutout_maker.py
sclassifier/data_aereco_checker.py
sclassifier/data_checker.py
sclassifier/data_generator.py
sclassifier/data_loader.py
sclassifier/data_provider.py
sclassifier/feature_extractor.py
sclassifier/feature_extractor_ae.py
sclassifier/feature_extractor_byol.py
sclassifier/feature_extractor_mom.py
sclassifier/feature_extractor_simclr.py
sclassifier/feature_extractor_umap.py
sclassifier/feature_merger.py
sclassifier/feature_selector.py
sclassifier/models.py
sclassifier/montage_utils.py
sclassifier/outlier_finder.py
sclassifier/pipeline.py
sclassifier/preprocessing.py
sclassifier/spectral_index_tt.py
sclassifier/tf_utils.py
sclassifier/utils.py
sclassifier.egg-info/PKG-INFO
sclassifier.egg-info/SOURCES.txt
sclassifier.egg-info/dependency_links.txt
sclassifier.egg-info/requires.txt
sclassifier.egg-info/top_level.txt
scripts/check_data.py
scripts/classify_source.py
scripts/compute_img_complexity.py
scripts/compute_latent_space_complexity.py
scripts/extract_features.py
scripts/find_outliers.py
scripts/gradcam.py
scripts/merge_features.py
scripts/read_model_weights.py
scripts/reconstruct_data.py
scripts/run_ae.py
scripts/run_byol.py
scripts/run_classifier.py
scripts/run_classifier_nn.py
scripts/run_clustering.py
scripts/run_imgclassifier.py
scripts/run_pca.py
scripts/run_pipeline.py
scripts/run_predict.py
scripts/run_simclr.py
scripts/run_umap.py
scripts/run_umap_on_imgs.py
scripts/select_features.py
scripts/set_encoder_weights_from_model.py