Metadata-Version: 2.1
Name: sclassifier
Version: 1.0.2
Summary: Source classification using supervised and self-supervised learning
Home-page: https://github.com/SKA-INAF/sclassifier
Author: Simone Riggi
Author-email: simone.riggi@gmail.com
License: GPL3
Download-URL: https://github.com/SKA-INAF/sclassifier/archive/refs/tags/v1.0.2.tar.gz
Keywords: radio,source,classification
Platform: UNKNOWN
Classifier: Development Status :: 5 - Production/Stable
Classifier: Intended Audience :: Science/Research
Classifier: Topic :: Scientific/Engineering :: Astronomy
Classifier: License :: OSI Approved :: GNU General Public License v3 (GPLv3)
Classifier: Programming Language :: Python :: 3
